aalu/__init__.py
aalu/backends/__init__.py
aalu/backends/base.py
aalu/backends/file.py
aalu/core/__init__.py
aalu/core/worker.py
aalu/interface/__init__.py
aalu/interface/base.py
aalu/interface/langchain.py
aalu-0.0.0.dist-info/METADATA
aalu-0.0.0.dist-info/WHEEL
aalu-0.0.0.dist-info/RECORD
