Metadata-Version: 2.1
Name: aalu
Version: 0.0.0
Summary: 
Author: Madhup Sukoon
Author-email: 29144316+vagrantism@users.noreply.github.com
Requires-Python: >=3.11,<4.0
Classifier: Programming Language :: Python :: 3
Classifier: Programming Language :: Python :: 3.11
Classifier: Programming Language :: Python :: 3.12
Requires-Dist: black (>=24.8.0,<25.0.0)
Requires-Dist: fastapi (>=0.112.0,<0.113.0)
Requires-Dist: jsonalias (>=0.1.2,<0.2.0)
Requires-Dist: langchain (>=0.2.12,<0.3.0)
Requires-Dist: langchain-core (>=0.2.28,<0.3.0)
Requires-Dist: langchain-google-genai (>=1.0.8,<2.0.0)
Requires-Dist: langchain-google-vertexai (>=1.0.8,<2.0.0)
Requires-Dist: langchain-openai (>=0.1.21,<0.2.0)
Requires-Dist: loguru (>=0.7.2,<0.8.0)
Requires-Dist: mypy (>=1.11.1,<2.0.0)
Requires-Dist: pydantic (>=2.8.2,<3.0.0)
Requires-Dist: python-dotenv (>=1.0.1,<2.0.0)
Requires-Dist: smart-open[all] (>=7.0.4,<8.0.0)
